{
  "movie": {
    "adult": false,
    "backdrop_path": "/byRNEm1QwfQC1Mn0K4gLM2fIfWO.jpg",
    "belongs_to_collection": null,
    "budget": 0,
    "genres": [
      {
        "id": 99,
        "name": "Documentary"
      }
    ],
    "homepage": "https://mk2films.com/en/film/the-man-with-a-camera-aka-living-russia",
    "id": 26317,
    "imdb_id": "tt0019760",
    "origin_country": [
      "SU"
    ],
    "original_language": "ru",
    "original_title": "\u0427\u0435\u043b\u043e\u0432\u0435\u043a \u0441 \u043a\u0438\u043d\u043e\u0430\u043f\u043f\u0430\u0440\u0430\u0442\u043e\u043c",
    "overview": "A cameraman wanders around with a camera slung over his shoulder, documenting urban life with dazzling inventiveness.",
    "popularity": 1.3221,
    "poster_path": "/vJgAdgJWX54v0oXfIvhwjlZnmgn.jpg",
    "production_companies": [
      {
        "id": 25065,
        "logo_path": "/ugfX3cgasxoDtUjkmWqlthK4hja.png",
        "name": "VUFKU",
        "origin_country": "SU"
      }
    ],
    "production_countries": [
      {
        "iso_3166_1": "SU",
        "name": "Soviet Union"
      }
    ],
    "release_date": "1929-05-12",
    "revenue": 0,
    "runtime": 68,
    "spoken_languages": [
      {
        "english_name": "No Language",
        "iso_639_1": "xx",
        "name": "No Language"
      }
    ],
    "status": "Released",
    "tagline": "The Greatest Documentary Ever Made",
    "title": "Man with a Movie Camera",
    "video": false,
    "vote_average": 7.835,
    "vote_count": 785
  },
  "credits": {
    "id": 26317,
    "cast": [
      {
        "adult": false,
        "gender": 2,
        "id": 1042437,
        "known_for_department": "Directing",
        "name": "Mikhail Kaufman",
        "original_name": "Mikhail Kaufman",
        "popularity": 0.6305,
        "profile_path": "/o2EH1WP2Qu271ToI63okSZwCzTF.jpg",
        "cast_id": 4,
        "character": "The Cameraman",
        "credit_id": "52fe44fac3a368484e041ab7",
        "order": 0
      }
    ],
    "crew": [
      {
        "adult": false,
        "gender": 0,
        "id": 95115,
        "known_for_department": "Production",
        "name": "Star Mishkel-Eneva",
        "original_name": "Star Mishkel-Eneva",
        "popularity": 0.017,
        "profile_path": null,
        "credit_id": "52fe44fac3a368484e041ab3",
        "department": "Production",
        "job": "Producer"
      },
      {
        "adult": false,
        "gender": 2,
        "id": 95111,
        "known_for_department": "Directing",
        "name": "Dziga Vertov",
        "original_name": "Dziga Vertov",
        "popularity": 0.1926,
        "profile_path": "/6CvXGGtNiF3ofSe1MFtGwgJnCVo.jpg",
        "credit_id": "52fe44fac3a368484e041aad",
        "department": "Directing",
        "job": "Director"
      },
      {
        "adult": false,
        "gender": 2,
        "id": 1042437,
        "known_for_department": "Directing",
        "name": "Mikhail Kaufman",
        "original_name": "Mikhail Kaufman",
        "popularity": 0.6305,
        "profile_path": "/o2EH1WP2Qu271ToI63okSZwCzTF.jpg",
        "credit_id": "64fda5f7e0ca7f010de8e141",
        "department": "Camera",
        "job": "Director of Photography"
      },
      {
        "adult": false,
        "gender": 2,
        "id": 1550009,
        "known_for_department": "Camera",
        "name": "Gleb Troyanski",
        "original_name": "Gleb Troyanski",
        "popularity": 0.0931,
        "profile_path": null,
        "credit_id": "64fda5e9ffc9de0ee17598ca",
        "department": "Camera",
        "job": "Director of Photography"
      },
      {
        "adult": false,
        "gender": 2,
        "id": 95111,
        "known_for_department": "Directing",
        "name": "Dziga Vertov",
        "original_name": "Dziga Vertov",
        "popularity": 0.1926,
        "profile_path": "/6CvXGGtNiF3ofSe1MFtGwgJnCVo.jpg",
        "credit_id": "5b91faf20e0a266099005258",
        "department": "Writing",
        "job": "Writer"
      },
      {
        "adult": false,
        "gender": 1,
        "id": 1057498,
        "known_for_department": "Directing",
        "name": "Elizaveta Svilova",
        "original_name": "\u0415\u043b\u0438\u0437\u0430\u0432\u0435\u0442\u0430 \u0421\u0432\u0438\u043b\u043e\u0432\u0430",
        "popularity": 1.0596,
        "profile_path": "/mvcgUvZ12Qa1Ut2nE6Zx6CRNmiX.jpg",
        "credit_id": "5b91fb5c9251416f60004911",
        "department": "Editing",
        "job": "Editor"
      }
    ]
  },
  "videos": {
    "id": 26317,
    "results": [
      {
        "iso_639_1": "en",
        "iso_3166_1": "US",
        "name": "2014 Restoration Trailer",
        "key": "BtTlgxtoqhg",
        "site": "YouTube",
        "size": 1080,
        "type": "Trailer",
        "official": true,
        "published_at": "2015-07-15T12:51:30.000Z",
        "id": "5fff5436678259003e9b6ff0"
      }
    ]
  },
  "keywords": {
    "id": 26317,
    "keywords": [
      {
        "id": 2111,
        "name": "soviet union"
      },
      {
        "id": 3232,
        "name": "odessa, ukraine"
      },
      {
        "id": 12999,
        "name": "black and white"
      },
      {
        "id": 33896,
        "name": "montage"
      },
      {
        "id": 154802,
        "name": "silent film"
      },
      {
        "id": 169734,
        "name": "cameraman"
      },
      {
        "id": 186450,
        "name": "moscow, russia"
      },
      {
        "id": 207876,
        "name": "1920s"
      },
      {
        "id": 212968,
        "name": "kyiv (kiev), ukraine"
      },
      {
        "id": 220141,
        "name": "city symphony"
      },
      {
        "id": 224427,
        "name": "soviet realism"
      },
      {
        "id": 256354,
        "name": "semi-fiction"
      },
      {
        "id": 283800,
        "name": "docufiction"
      },
      {
        "id": 297181,
        "name": "kharkiv (kharkov), ukraine"
      },
      {
        "id": 315053,
        "name": "critical"
      }
    ]
  },
  "watch_providers": {
    "id": 26317,
    "results": {
      "AD": {
        "link": "https://www.themoviedb.org/movie/26317/watch?locale=AD",
        "free": [
          {
            "logo_path": "/g2IaWyo6jCY0rIFjb4qgZ0bSmm3.jpg",
            "provider_id": 2285,
            "provider_name": "JustWatch TV",
            "display_priority": 25
          }
        ]
      },
      "AE": {
        "link": "https://www.themoviedb.org/movie/26317/watch?locale=AE",
        "free": [
          {
            "logo_path": "/g2IaWyo6jCY0rIFjb4qgZ0bSmm3.jpg",
            "provider_id": 2285,
            "provider_name": "JustWatch TV",
            "display_priority": 18
          }
        ]
      },
      "AG": {
        "link": "https://www.themoviedb.org/movie/26317/watch?locale=AG",
        "free": [
          {
            "logo_path": "/g2IaWyo6jCY0rIFjb4qgZ0bSmm3.jpg",
            "provider_id": 2285,
            "provider_name": "JustWatch TV",
            "display_priority": 13
          }
        ]
      },
      "AL": {
        "link": "https://www.themoviedb.org/movie/26317/watch?locale=AL",
        "free": [
          {
            "logo_path": "/g2IaWyo6jCY0rIFjb4qgZ0bSmm3.jpg",
            "provider_id": 2285,
            "provider_name": "JustWatch TV",
            "display_priority": 27
          }
        ]
      },
      "AO": {
        "link": "https://www.themoviedb.org/movie/26317/watch?locale=AO",
        "free": [
          {
            "logo_path": "/g2IaWyo6jCY0rIFjb4qgZ0bSmm3.jpg",
            "provider_id": 2285,
            "provider_name": "JustWatch TV",
            "display_priority": 5
          }
        ]
      },
      "AR": {
        "link": "https://www.themoviedb.org/movie/26317/watch?locale=AR",
        "free": [
          {
            "logo_path": "/g2IaWyo6jCY0rIFjb4qgZ0bSmm3.jpg",
            "provider_id": 2285,
            "provider_name": "JustWatch TV",
            "display_priority": 40
          }
        ]
      },
      "AT": {
        "link": "https://www.themoviedb.org/movie/26317/watch?locale=AT",
        "buy": [
          {
            "logo_path": "/1syoSwH2yIskHUqeOiK9re8AMJC.jpg",
            "provider_id": 310,
            "provider_name": "LaCinetek",
            "display_priority": 23
          }
        ],
        "free": [
          {
            "logo_path": "/g2IaWyo6jCY0rIFjb4qgZ0bSmm3.jpg",
            "provider_id": 2285,
            "provider_name": "JustWatch TV",
            "display_priority": 112
          }
        ],
        "flatrate": [
          {
            "logo_path": "/eKVmLFHW5PeNhuR7Nedd8OIxW2M.jpg",
            "provider_id": 100,
            "provider_name": "GuideDoc",
            "display_priority": 15
          },
          {
            "logo_path": "/1syoSwH2yIskHUqeOiK9re8AMJC.jpg",
            "provider_id": 310,
            "provider_name": "LaCinetek",
            "display_priority": 23
          },
          {
            "logo_path": "/x570VpH2C9EKDf1riP83rYc5dnL.jpg",
            "provider_id": 11,
            "provider_name": "MUBI",
            "display_priority": 145
          },
          {
            "logo_path": "/a4IDLKjvP5gvq7tNlg2Xw5YyEkI.jpg",
            "provider_id": 201,
            "provider_name": "MUBI Amazon Channel",
            "display_priority": 146
          }
        ],
        "rent": [
          {
            "logo_path": "/1syoSwH2yIskHUqeOiK9re8AMJC.jpg",
            "provider_id": 310,
            "provider_name": "LaCinetek",
            "display_priority": 23
          }
        ]
      },
      "AU": {
        "link": "https://www.themoviedb.org/movie/26317/watch?locale=AU",
        "flatrate": [
          {
            "logo_path": "/eKVmLFHW5PeNhuR7Nedd8OIxW2M.jpg",
            "provider_id": 100,
            "provider_name": "GuideDoc",
            "display_priority": 26
          }
        ],
        "free": [
          {
            "logo_path": "/g2IaWyo6jCY0rIFjb4qgZ0bSmm3.jpg",
            "provider_id": 2285,
            "provider_name": "JustWatch TV",
            "display_priority": 5
          }
        ]
      },
      "AZ": {
        "link": "https://www.themoviedb.org/movie/26317/watch?locale=AZ",
        "free": [
          {
            "logo_path": "/g2IaWyo6jCY0rIFjb4qgZ0bSmm3.jpg",
            "provider_id": 2285,
            "provider_name": "JustWatch TV",
            "display_priority": 6
          }
        ]
      },
      "BA": {
        "link": "https://www.themoviedb.org/movie/26317/watch?locale=BA",
        "free": [
          {
            "logo_path": "/g2IaWyo6jCY0rIFjb4qgZ0bSmm3.jpg",
            "provider_id": 2285,
            "provider_name": "JustWatch TV",
            "display_priority": 28
          }
        ]
      },
      "BB": {
        "link": "https://www.themoviedb.org/movie/26317/watch?locale=BB",
        "free": [
          {
            "logo_path": "/g2IaWyo6jCY0rIFjb4qgZ0bSmm3.jpg",
            "provider_id": 2285,
            "provider_name": "JustWatch TV",
            "display_priority": 25
          }
        ]
      },
      "BE": {
        "link": "https://www.themoviedb.org/movie/26317/watch?locale=BE",
        "free": [
          {
            "logo_path": "/g2IaWyo6jCY0rIFjb4qgZ0bSmm3.jpg",
            "provider_id": 2285,
            "provider_name": "JustWatch TV",
            "display_priority": 39
          }
        ],
        "buy": [
          {
            "logo_path": "/1syoSwH2yIskHUqeOiK9re8AMJC.jpg",
            "provider_id": 310,
            "provider_name": "LaCinetek",
            "display_priority": 15
          }
        ],
        "rent": [
          {
            "logo_path": "/1syoSwH2yIskHUqeOiK9re8AMJC.jpg",
            "provider_id": 310,
            "provider_name": "LaCinetek",
            "display_priority": 15
          }
        ],
        "flatrate": [
          {
            "logo_path": "/1syoSwH2yIskHUqeOiK9re8AMJC.jpg",
            "provider_id": 310,
            "provider_name": "LaCinetek",
            "display_priority": 15
          }
        ]
      },
      "BF": {
        "link": "https://www.themoviedb.org/movie/26317/watch?locale=BF",
        "free": [
          {
            "logo_path": "/g2IaWyo6jCY0rIFjb4qgZ0bSmm3.jpg",
            "provider_id": 2285,
            "provider_name": "JustWatch TV",
            "display_priority": 5
          }
        ]
      },
      "BG": {
        "link": "https://www.themoviedb.org/movie/26317/watch?locale=BG",
        "free": [
          {
            "logo_path": "/g2IaWyo6jCY0rIFjb4qgZ0bSmm3.jpg",
            "provider_id": 2285,
            "provider_name": "JustWatch TV",
            "display_priority": 22
          }
        ],
        "flatrate": [
          {
            "logo_path": "/eKVmLFHW5PeNhuR7Nedd8OIxW2M.jpg",
            "provider_id": 100,
            "provider_name": "GuideDoc",
            "display_priority": 9
          }
        ]
      },
      "BH": {
        "link": "https://www.themoviedb.org/movie/26317/watch?locale=BH",
        "free": [
          {
            "logo_path": "/g2IaWyo6jCY0rIFjb4qgZ0bSmm3.jpg",
            "provider_id": 2285,
            "provider_name": "JustWatch TV",
            "display_priority": 28
          }
        ]
      },
      "BM": {
        "link": "https://www.themoviedb.org/movie/26317/watch?locale=BM",
        "free": [
          {
            "logo_path": "/g2IaWyo6jCY0rIFjb4qgZ0bSmm3.jpg",
            "provider_id": 2285,
            "provider_name": "JustWatch TV",
            "display_priority": 27
          }
        ]
      },
      "BO": {
        "link": "https://www.themoviedb.org/movie/26317/watch?locale=BO",
        "flatrate": [
          {
            "logo_path": "/eKVmLFHW5PeNhuR7Nedd8OIxW2M.jpg",
            "provider_id": 100,
            "provider_name": "GuideDoc",
            "display_priority": 11
          }
        ],
        "free": [
          {
            "logo_path": "/g2IaWyo6jCY0rIFjb4qgZ0bSmm3.jpg",
            "provider_id": 2285,
            "provider_name": "JustWatch TV",
            "display_priority": 32
          }
        ]
      },
      "BR": {
        "link": "https://www.themoviedb.org/movie/26317/watch?locale=BR",
        "free": [
          {
            "logo_path": "/g2IaWyo6jCY0rIFjb4qgZ0bSmm3.jpg",
            "provider_id": 2285,
            "provider_name": "JustWatch TV",
            "display_priority": 70
          }
        ],
        "flatrate": [
          {
            "logo_path": "/gBYz3cTgDPRoRFOCS4gG9BNPJdX.jpg",
            "provider_id": 447,
            "provider_name": "Belas Artes \u00e0 La Carte",
            "display_priority": 16
          },
          {
            "logo_path": "/9kcTsX2laYclN4bFiMH3RuhZel2.jpg",
            "provider_id": 2156,
            "provider_name": "Telecine Amazon Channel",
            "display_priority": 56
          }
        ]
      },
      "BS": {
        "link": "https://www.themoviedb.org/movie/26317/watch?locale=BS",
        "free": [
          {
            "logo_path": "/g2IaWyo6jCY0rIFjb4qgZ0bSmm3.jpg",
            "provider_id": 2285,
            "provider_name": "JustWatch TV",
            "display_priority": 26
          }
        ]
      },
      "BY": {
        "link": "https://www.themoviedb.org/movie/26317/watch?locale=BY",
        "free": [
          {
            "logo_path": "/g2IaWyo6jCY0rIFjb4qgZ0bSmm3.jpg",
            "provider_id": 2285,
            "provider_name": "JustWatch TV",
            "display_priority": 6
          }
        ]
      },
      "BZ": {
        "link": "https://www.themoviedb.org/movie/26317/watch?locale=BZ",
        "free": [
          {
            "logo_path": "/g2IaWyo6jCY0rIFjb4qgZ0bSmm3.jpg",
            "provider_id": 2285,
            "provider_name": "JustWatch TV",
            "display_priority": 11
          }
        ]
      },
      "CA": {
        "link": "https://www.themoviedb.org/movie/26317/watch?locale=CA",
        "buy": [
          {
            "logo_path": "/SPnB1qiCkYfirS2it3hZORwGVn.jpg",
            "provider_id": 2,
            "provider_name": "Apple TV Store",
            "display_priority": 5
          }
        ],
        "flatrate": [
          {
            "logo_path": "/eKVmLFHW5PeNhuR7Nedd8OIxW2M.jpg",
            "provider_id": 100,
            "provider_name": "GuideDoc",
            "display_priority": 37
          }
        ],
        "free": [
          {
            "logo_path": "/g2IaWyo6jCY0rIFjb4qgZ0bSmm3.jpg",
            "provider_id": 2285,
            "provider_name": "JustWatch TV",
            "display_priority": 120
          }
        ],
        "rent": [
          {
            "logo_path": "/SPnB1qiCkYfirS2it3hZORwGVn.jpg",
            "provider_id": 2,
            "provider_name": "Apple TV Store",
            "display_priority": 5
          }
        ]
      },
      "CD": {
        "link": "https://www.themoviedb.org/movie/26317/watch?locale=CD",
        "free": [
          {
            "logo_path": "/g2IaWyo6jCY0rIFjb4qgZ0bSmm3.jpg",
            "provider_id": 2285,
            "provider_name": "JustWatch TV",
            "display_priority": 2
          }
        ]
      },
      "CH": {
        "link": "https://www.themoviedb.org/movie/26317/watch?locale=CH",
        "free": [
          {
            "logo_path": "/g2IaWyo6jCY0rIFjb4qgZ0bSmm3.jpg",
            "provider_id": 2285,
            "provider_name": "JustWatch TV",
            "display_priority": 60
          }
        ],
        "flatrate": [
          {
            "logo_path": "/eKVmLFHW5PeNhuR7Nedd8OIxW2M.jpg",
            "provider_id": 100,
            "provider_name": "GuideDoc",
            "display_priority": 10
          },
          {
            "logo_path": "/x570VpH2C9EKDf1riP83rYc5dnL.jpg",
            "provider_id": 11,
            "provider_name": "MUBI",
            "display_priority": 69
          }
        ]
      },
      "CI": {
        "link": "https://www.themoviedb.org/movie/26317/watch?locale=CI",
        "free": [
          {
            "logo_path": "/g2IaWyo6jCY0rIFjb4qgZ0bSmm3.jpg",
            "provider_id": 2285,
            "provider_name": "JustWatch TV",
            "display_priority": 26
          }
        ]
      },
      "CL": {
        "link": "https://www.themoviedb.org/movie/26317/watch?locale=CL",
        "free": [
          {
            "logo_path": "/g2IaWyo6jCY0rIFjb4qgZ0bSmm3.jpg",
            "provider_id": 2285,
            "provider_name": "JustWatch TV",
            "display_priority": 43
          }
        ]
      },
      "CM": {
        "link": "https://www.themoviedb.org/movie/26317/watch?locale=CM",
        "free": [
          {
            "logo_path": "/g2IaWyo6jCY0rIFjb4qgZ0bSmm3.jpg",
            "provider_id": 2285,
            "provider_name": "JustWatch TV",
            "display_priority": 5
          }
        ]
      },
      "CO": {
        "link": "https://www.themoviedb.org/movie/26317/watch?locale=CO",
        "free": [
          {
            "logo_path": "/g2IaWyo6jCY0rIFjb4qgZ0bSmm3.jpg",
            "provider_id": 2285,
            "provider_name": "JustWatch TV",
            "display_priority": 44
          }
        ]
      },
      "CR": {
        "link": "https://www.themoviedb.org/movie/26317/watch?locale=CR",
        "free": [
          {
            "logo_path": "/g2IaWyo6jCY0rIFjb4qgZ0bSmm3.jpg",
            "provider_id": 2285,
            "provider_name": "JustWatch TV",
            "display_priority": 32
          }
        ],
        "flatrate": [
          {
            "logo_path": "/eKVmLFHW5PeNhuR7Nedd8OIxW2M.jpg",
            "provider_id": 100,
            "provider_name": "GuideDoc",
            "display_priority": 9
          }
        ]
      },
      "CU": {
        "link": "https://www.themoviedb.org/movie/26317/watch?locale=CU",
        "free": [
          {
            "logo_path": "/g2IaWyo6jCY0rIFjb4qgZ0bSmm3.jpg",
            "provider_id": 2285,
            "provider_name": "JustWatch TV",
            "display_priority": 8
          }
        ]
      },
      "CV": {
        "link": "https://www.themoviedb.org/movie/26317/watch?locale=CV",
        "free": [
          {
            "logo_path": "/g2IaWyo6jCY0rIFjb4qgZ0bSmm3.jpg",
            "provider_id": 2285,
            "provider_name": "JustWatch TV",
            "display_priority": 13
          }
        ]
      },
      "CY": {
        "link": "https://www.themoviedb.org/movie/26317/watch?locale=CY",
        "free": [
          {
            "logo_path": "/g2IaWyo6jCY0rIFjb4qgZ0bSmm3.jpg",
            "provider_id": 2285,
            "provider_name": "JustWatch TV",
            "display_priority": 10
          }
        ]
      },
      "CZ": {
        "link": "https://www.themoviedb.org/movie/26317/watch?locale=CZ",
        "free": [
          {
            "logo_path": "/g2IaWyo6jCY0rIFjb4qgZ0bSmm3.jpg",
            "provider_id": 2285,
            "provider_name": "JustWatch TV",
            "display_priority": 31
          }
        ]
      },
      "DE": {
        "link": "https://www.themoviedb.org/movie/26317/watch?locale=DE",
        "free": [
          {
            "logo_path": "/g2IaWyo6jCY0rIFjb4qgZ0bSmm3.jpg",
            "provider_id": 2285,
            "provider_name": "JustWatch TV",
            "display_priority": 48
          }
        ],
        "rent": [
          {
            "logo_path": "/1syoSwH2yIskHUqeOiK9re8AMJC.jpg",
            "provider_id": 310,
            "provider_name": "LaCinetek",
            "display_priority": 44
          }
        ],
        "buy": [
          {
            "logo_path": "/1syoSwH2yIskHUqeOiK9re8AMJC.jpg",
            "provider_id": 310,
            "provider_name": "LaCinetek",
            "display_priority": 44
          }
        ],
        "flatrate": [
          {
            "logo_path": "/x570VpH2C9EKDf1riP83rYc5dnL.jpg",
            "provider_id": 11,
            "provider_name": "MUBI",
            "display_priority": 24
          },
          {
            "logo_path": "/eKVmLFHW5PeNhuR7Nedd8OIxW2M.jpg",
            "provider_id": 100,
            "provider_name": "GuideDoc",
            "display_priority": 28
          },
          {
            "logo_path": "/a4IDLKjvP5gvq7tNlg2Xw5YyEkI.jpg",
            "provider_id": 201,
            "provider_name": "MUBI Amazon Channel",
            "display_priority": 31
          },
          {
            "logo_path": "/1syoSwH2yIskHUqeOiK9re8AMJC.jpg",
            "provider_id": 310,
            "provider_name": "LaCinetek",
            "display_priority": 44
          }
        ]
      },
      "DK": {
        "link": "https://www.themoviedb.org/movie/26317/watch?locale=DK",
        "free": [
          {
            "logo_path": "/g2IaWyo6jCY0rIFjb4qgZ0bSmm3.jpg",
            "provider_id": 2285,
            "provider_name": "JustWatch TV",
            "display_priority": 40
          }
        ],
        "flatrate": [
          {
            "logo_path": "/eKVmLFHW5PeNhuR7Nedd8OIxW2M.jpg",
            "provider_id": 100,
            "provider_name": "GuideDoc",
            "display_priority": 9
          }
        ]
      },
      "DO": {
        "link": "https://www.themoviedb.org/movie/26317/watch?locale=DO",
        "free": [
          {
            "logo_path": "/g2IaWyo6jCY0rIFjb4qgZ0bSmm3.jpg",
            "provider_id": 2285,
            "provider_name": "JustWatch TV",
            "display_priority": 32
          }
        ]
      },
      "DZ": {
        "link": "https://www.themoviedb.org/movie/26317/watch?locale=DZ",
        "free": [
          {
            "logo_path": "/g2IaWyo6jCY0rIFjb4qgZ0bSmm3.jpg",
            "provider_id": 2285,
            "provider_name": "JustWatch TV",
            "display_priority": 28
          }
        ]
      },
      "EC": {
        "link": "https://www.themoviedb.org/movie/26317/watch?locale=EC",
        "free": [
          {
            "logo_path": "/g2IaWyo6jCY0rIFjb4qgZ0bSmm3.jpg",
            "provider_id": 2285,
            "provider_name": "JustWatch TV",
            "display_priority": 31
          }
        ]
      },
      "EE": {
        "link": "https://www.themoviedb.org/movie/26317/watch?locale=EE",
        "free": [
          {
            "logo_path": "/g2IaWyo6jCY0rIFjb4qgZ0bSmm3.jpg",
            "provider_id": 2285,
            "provider_name": "JustWatch TV",
            "display_priority": 26
          }
        ],
        "flatrate": [
          {
            "logo_path": "/eKVmLFHW5PeNhuR7Nedd8OIxW2M.jpg",
            "provider_id": 100,
            "provider_name": "GuideDoc",
            "display_priority": 4
          }
        ]
      },
      "EG": {
        "link": "https://www.themoviedb.org/movie/26317/watch?locale=EG",
        "free": [
          {
            "logo_path": "/g2IaWyo6jCY0rIFjb4qgZ0bSmm3.jpg",
            "provider_id": 2285,
            "provider_name": "JustWatch TV",
            "display_priority": 33
          }
        ]
      },
      "ES": {
        "link": "https://www.themoviedb.org/movie/26317/watch?locale=ES",
        "flatrate": [
          {
            "logo_path": "/eKVmLFHW5PeNhuR7Nedd8OIxW2M.jpg",
            "provider_id": 100,
            "provider_name": "GuideDoc",
            "display_priority": 18
          }
        ],
        "free": [
          {
            "logo_path": "/g2IaWyo6jCY0rIFjb4qgZ0bSmm3.jpg",
            "provider_id": 2285,
            "provider_name": "JustWatch TV",
            "display_priority": 71
          }
        ]
      },
      "FI": {
        "link": "https://www.themoviedb.org/movie/26317/watch?locale=FI",
        "flatrate": [
          {
            "logo_path": "/eKVmLFHW5PeNhuR7Nedd8OIxW2M.jpg",
            "provider_id": 100,
            "provider_name": "GuideDoc",
            "display_priority": 10
          },
          {
            "logo_path": "/4SJW6thrCvN6ya2hO6naksfRZDF.jpg",
            "provider_id": 287,
            "provider_name": "BFI Player Amazon Channel",
            "display_priority": 53
          }
        ],
        "free": [
          {
            "logo_path": "/g2IaWyo6jCY0rIFjb4qgZ0bSmm3.jpg",
            "provider_id": 2285,
            "provider_name": "JustWatch TV",
            "display_priority": 42
          }
        ]
      },
      "FJ": {
        "link": "https://www.themoviedb.org/movie/26317/watch?locale=FJ",
        "free": [
          {
            "logo_path": "/g2IaWyo6jCY0rIFjb4qgZ0bSmm3.jpg",
            "provider_id": 2285,
            "provider_name": "JustWatch TV",
            "display_priority": 12
          }
        ]
      },
      "FR": {
        "link": "https://www.themoviedb.org/movie/26317/watch?locale=FR",
        "buy": [
          {
            "logo_path": "/9Fyo6njYvroAIxAzTBbLgnjgYga.jpg",
            "provider_id": 61,
            "provider_name": "Orange VOD",
            "display_priority": 12
          },
          {
            "logo_path": "/1syoSwH2yIskHUqeOiK9re8AMJC.jpg",
            "provider_id": 310,
            "provider_name": "LaCinetek",
            "display_priority": 21
          },
          {
            "logo_path": "/11Yzww3g6lYZznKrom3cSrKP4St.jpg",
            "provider_id": 239,
            "provider_name": "Universcine",
            "display_priority": 35
          },
          {
            "logo_path": "/1gtidYfh89iLkGcbhPtr1lvx47W.jpg",
            "provider_id": 2671,
            "provider_name": "ARTE Boutique",
            "display_priority": 109
          }
        ],
        "flatrate": [
          {
            "logo_path": "/1syoSwH2yIskHUqeOiK9re8AMJC.jpg",
            "provider_id": 310,
            "provider_name": "LaCinetek",
            "display_priority": 21
          },
          {
            "logo_path": "/7up8PVB6RaL0fDs5XFzjJlq9mg2.jpg",
            "provider_id": 550,
            "provider_name": "Tenk",
            "display_priority": 30
          }
        ],
        "free": [
          {
            "logo_path": "/g2IaWyo6jCY0rIFjb4qgZ0bSmm3.jpg",
            "provider_id": 2285,
            "provider_name": "JustWatch TV",
            "display_priority": 81
          }
        ],
        "rent": [
          {
            "logo_path": "/9Fyo6njYvroAIxAzTBbLgnjgYga.jpg",
            "provider_id": 61,
            "provider_name": "Orange VOD",
            "display_priority": 12
          },
          {
            "logo_path": "/1syoSwH2yIskHUqeOiK9re8AMJC.jpg",
            "provider_id": 310,
            "provider_name": "LaCinetek",
            "display_priority": 21
          },
          {
            "logo_path": "/11Yzww3g6lYZznKrom3cSrKP4St.jpg",
            "provider_id": 239,
            "provider_name": "Universcine",
            "display_priority": 35
          },
          {
            "logo_path": "/1gtidYfh89iLkGcbhPtr1lvx47W.jpg",
            "provider_id": 2671,
            "provider_name": "ARTE Boutique",
            "display_priority": 109
          }
        ]
      },
      "GB": {
        "link": "https://www.themoviedb.org/movie/26317/watch?locale=GB",
        "free": [
          {
            "logo_path": "/g2IaWyo6jCY0rIFjb4qgZ0bSmm3.jpg",
            "provider_id": 2285,
            "provider_name": "JustWatch TV",
            "display_priority": 44
          }
        ],
        "buy": [
          {
            "logo_path": "/SPnB1qiCkYfirS2it3hZORwGVn.jpg",
            "provider_id": 2,
            "provider_name": "Apple TV Store",
            "display_priority": 4
          },
          {
            "logo_path": "/qR6FKvnPBx2O37FDg8PNM7efwF3.jpg",
            "provider_id": 10,
            "provider_name": "Amazon Video",
            "display_priority": 7
          }
        ],
        "rent": [
          {
            "logo_path": "/SPnB1qiCkYfirS2it3hZORwGVn.jpg",
            "provider_id": 2,
            "provider_name": "Apple TV Store",
            "display_priority": 4
          },
          {
            "logo_path": "/qR6FKvnPBx2O37FDg8PNM7efwF3.jpg",
            "provider_id": 10,
            "provider_name": "Amazon Video",
            "display_priority": 7
          }
        ],
        "flatrate": [
          {
            "logo_path": "/erGoVIuKJ0PYOJ8dh62o4YhwaJK.jpg",
            "provider_id": 224,
            "provider_name": "BFI Player",
            "display_priority": 19
          },
          {
            "logo_path": "/eKVmLFHW5PeNhuR7Nedd8OIxW2M.jpg",
            "provider_id": 100,
            "provider_name": "GuideDoc",
            "display_priority": 26
          },
          {
            "logo_path": "/4SJW6thrCvN6ya2hO6naksfRZDF.jpg",
            "provider_id": 287,
            "provider_name": "BFI Player Amazon Channel",
            "display_priority": 30
          },
          {
            "logo_path": "/kohVS01u3sP5IkqsSaAKdBit6aP.jpg",
            "provider_id": 2041,
            "provider_name": "BFI Player Apple TV Channel",
            "display_priority": 97
          }
        ]
      },
      "GF": {
        "link": "https://www.themoviedb.org/movie/26317/watch?locale=GF",
        "free": [
          {
            "logo_path": "/g2IaWyo6jCY0rIFjb4qgZ0bSmm3.jpg",
            "provider_id": 2285,
            "provider_name": "JustWatch TV",
            "display_priority": 26
          }
        ]
      },
      "GG": {
        "link": "https://www.themoviedb.org/movie/26317/watch?locale=GG",
        "flatrate": [
          {
            "logo_path": "/4SJW6thrCvN6ya2hO6naksfRZDF.jpg",
            "provider_id": 287,
            "provider_name": "BFI Player Amazon Channel",
            "display_priority": 30
          }
        ],
        "free": [
          {
            "logo_path": "/g2IaWyo6jCY0rIFjb4qgZ0bSmm3.jpg",
            "provider_id": 2285,
            "provider_name": "JustWatch TV",
            "display_priority": 18
          }
        ],
        "rent": [
          {
            "logo_path": "/qR6FKvnPBx2O37FDg8PNM7efwF3.jpg",
            "provider_id": 10,
            "provider_name": "Amazon Video",
            "display_priority": 84
          }
        ],
        "buy": [
          {
            "logo_path": "/qR6FKvnPBx2O37FDg8PNM7efwF3.jpg",
            "provider_id": 10,
            "provider_name": "Amazon Video",
            "display_priority": 84
          }
        ]
      },
      "GH": {
        "link": "https://www.themoviedb.org/movie/26317/watch?locale=GH",
        "free": [
          {
            "logo_path": "/g2IaWyo6jCY0rIFjb4qgZ0bSmm3.jpg",
            "provider_id": 2285,
            "provider_name": "JustWatch TV",
            "display_priority": 16
          }
        ]
      },
      "GI": {
        "link": "https://www.themoviedb.org/movie/26317/watch?locale=GI",
        "free": [
          {
            "logo_path": "/g2IaWyo6jCY0rIFjb4qgZ0bSmm3.jpg",
            "provider_id": 2285,
            "provider_name": "JustWatch TV",
            "display_priority": 26
          }
        ]
      },
      "GQ": {
        "link": "https://www.themoviedb.org/movie/26317/watch?locale=GQ",
        "free": [
          {
            "logo_path": "/g2IaWyo6jCY0rIFjb4qgZ0bSmm3.jpg",
            "provider_id": 2285,
            "provider_name": "JustWatch TV",
            "display_priority": 14
          }
        ]
      },
      "GR": {
        "link": "https://www.themoviedb.org/movie/26317/watch?locale=GR",
        "free": [
          {
            "logo_path": "/g2IaWyo6jCY0rIFjb4qgZ0bSmm3.jpg",
            "provider_id": 2285,
            "provider_name": "JustWatch TV",
            "display_priority": 24
          }
        ]
      },
      "GT": {
        "link": "https://www.themoviedb.org/movie/26317/watch?locale=GT",
        "flatrate": [
          {
            "logo_path": "/eKVmLFHW5PeNhuR7Nedd8OIxW2M.jpg",
            "provider_id": 100,
            "provider_name": "GuideDoc",
            "display_priority": 9
          }
        ],
        "free": [
          {
            "logo_path": "/g2IaWyo6jCY0rIFjb4qgZ0bSmm3.jpg",
            "provider_id": 2285,
            "provider_name": "JustWatch TV",
            "display_priority": 32
          }
        ]
      },
      "GY": {
        "link": "https://www.themoviedb.org/movie/26317/watch?locale=GY",
        "free": [
          {
            "logo_path": "/g2IaWyo6jCY0rIFjb4qgZ0bSmm3.jpg",
            "provider_id": 2285,
            "provider_name": "JustWatch TV",
            "display_priority": 5
          }
        ]
      },
      "HK": {
        "link": "https://www.themoviedb.org/movie/26317/watch?locale=HK",
        "flatrate": [
          {
            "logo_path": "/eKVmLFHW5PeNhuR7Nedd8OIxW2M.jpg",
            "provider_id": 100,
            "provider_name": "GuideDoc",
            "display_priority": 25
          }
        ],
        "free": [
          {
            "logo_path": "/g2IaWyo6jCY0rIFjb4qgZ0bSmm3.jpg",
            "provider_id": 2285,
            "provider_name": "JustWatch TV",
            "display_priority": 37
          }
        ]
      },
      "HN": {
        "link": "https://www.themoviedb.org/movie/26317/watch?locale=HN",
        "free": [
          {
            "logo_path": "/g2IaWyo6jCY0rIFjb4qgZ0bSmm3.jpg",
            "provider_id": 2285,
            "provider_name": "JustWatch TV",
            "display_priority": 32
          }
        ]
      },
      "HR": {
        "link": "https://www.themoviedb.org/movie/26317/watch?locale=HR",
        "free": [
          {
            "logo_path": "/g2IaWyo6jCY0rIFjb4qgZ0bSmm3.jpg",
            "provider_id": 2285,
            "provider_name": "JustWatch TV",
            "display_priority": 34
          }
        ]
      },
      "HU": {
        "link": "https://www.themoviedb.org/movie/26317/watch?locale=HU",
        "free": [
          {
            "logo_path": "/g2IaWyo6jCY0rIFjb4qgZ0bSmm3.jpg",
            "provider_id": 2285,
            "provider_name": "JustWatch TV",
            "display_priority": 4
          }
        ]
      },
      "ID": {
        "link": "https://www.themoviedb.org/movie/26317/watch?locale=ID",
        "free": [
          {
            "logo_path": "/g2IaWyo6jCY0rIFjb4qgZ0bSmm3.jpg",
            "provider_id": 2285,
            "provider_name": "JustWatch TV",
            "display_priority": 37
          }
        ],
        "flatrate": [
          {
            "logo_path": "/eKVmLFHW5PeNhuR7Nedd8OIxW2M.jpg",
            "provider_id": 100,
            "provider_name": "GuideDoc",
            "display_priority": 7
          }
        ]
      },
      "IE": {
        "link": "https://www.themoviedb.org/movie/26317/watch?locale=IE",
        "buy": [
          {
            "logo_path": "/SPnB1qiCkYfirS2it3hZORwGVn.jpg",
            "provider_id": 2,
            "provider_name": "Apple TV Store",
            "display_priority": 4
          }
        ],
        "free": [
          {
            "logo_path": "/g2IaWyo6jCY0rIFjb4qgZ0bSmm3.jpg",
            "provider_id": 2285,
            "provider_name": "JustWatch TV",
            "display_priority": 44
          }
        ],
        "flatrate": [
          {
            "logo_path": "/eKVmLFHW5PeNhuR7Nedd8OIxW2M.jpg",
            "provider_id": 100,
            "provider_name": "GuideDoc",
            "display_priority": 13
          }
        ],
        "rent": [
          {
            "logo_path": "/SPnB1qiCkYfirS2it3hZORwGVn.jpg",
            "provider_id": 2,
            "provider_name": "Apple TV Store",
            "display_priority": 4
          }
        ]
      },
      "IL": {
        "link": "https://www.themoviedb.org/movie/26317/watch?locale=IL",
        "free": [
          {
            "logo_path": "/g2IaWyo6jCY0rIFjb4qgZ0bSmm3.jpg",
            "provider_id": 2285,
            "provider_name": "JustWatch TV",
            "display_priority": 26
          }
        ]
      },
      "IN": {
        "link": "https://www.themoviedb.org/movie/26317/watch?locale=IN",
        "flatrate": [
          {
            "logo_path": "/eKVmLFHW5PeNhuR7Nedd8OIxW2M.jpg",
            "provider_id": 100,
            "provider_name": "GuideDoc",
            "display_priority": 11
          }
        ],
        "free": [
          {
            "logo_path": "/g2IaWyo6jCY0rIFjb4qgZ0bSmm3.jpg",
            "provider_id": 2285,
            "provider_name": "JustWatch TV",
            "display_priority": 67
          }
        ]
      },
      "IQ": {
        "link": "https://www.themoviedb.org/movie/26317/watch?locale=IQ",
        "free": [
          {
            "logo_path": "/g2IaWyo6jCY0rIFjb4qgZ0bSmm3.jpg",
            "provider_id": 2285,
            "provider_name": "JustWatch TV",
            "display_priority": 29
          }
        ]
      },
      "IS": {
        "link": "https://www.themoviedb.org/movie/26317/watch?locale=IS",
        "free": [
          {
            "logo_path": "/g2IaWyo6jCY0rIFjb4qgZ0bSmm3.jpg",
            "provider_id": 2285,
            "provider_name": "JustWatch TV",
            "display_priority": 31
          }
        ]
      },
      "IT": {
        "link": "https://www.themoviedb.org/movie/26317/watch?locale=IT",
        "flatrate": [
          {
            "logo_path": "/x570VpH2C9EKDf1riP83rYc5dnL.jpg",
            "provider_id": 11,
            "provider_name": "MUBI",
            "display_priority": 12
          },
          {
            "logo_path": "/eKVmLFHW5PeNhuR7Nedd8OIxW2M.jpg",
            "provider_id": 100,
            "provider_name": "GuideDoc",
            "display_priority": 18
          },
          {
            "logo_path": "/a4IDLKjvP5gvq7tNlg2Xw5YyEkI.jpg",
            "provider_id": 201,
            "provider_name": "MUBI Amazon Channel",
            "display_priority": 47
          },
          {
            "logo_path": "/iayPGzRbLdE2kXDzvF5QTbRkEHe.jpg",
            "provider_id": 2483,
            "provider_name": "MYmovies One",
            "display_priority": 86
          }
        ],
        "free": [
          {
            "logo_path": "/g2IaWyo6jCY0rIFjb4qgZ0bSmm3.jpg",
            "provider_id": 2285,
            "provider_name": "JustWatch TV",
            "display_priority": 73
          }
        ]
      },
      "JM": {
        "link": "https://www.themoviedb.org/movie/26317/watch?locale=JM",
        "free": [
          {
            "logo_path": "/g2IaWyo6jCY0rIFjb4qgZ0bSmm3.jpg",
            "provider_id": 2285,
            "provider_name": "JustWatch TV",
            "display_priority": 25
          }
        ]
      },
      "JO": {
        "link": "https://www.themoviedb.org/movie/26317/watch?locale=JO",
        "free": [
          {
            "logo_path": "/g2IaWyo6jCY0rIFjb4qgZ0bSmm3.jpg",
            "provider_id": 2285,
            "provider_name": "JustWatch TV",
            "display_priority": 30
          }
        ]
      },
      "JP": {
        "link": "https://www.themoviedb.org/movie/26317/watch?locale=JP",
        "free": [
          {
            "logo_path": "/g2IaWyo6jCY0rIFjb4qgZ0bSmm3.jpg",
            "provider_id": 2285,
            "provider_name": "JustWatch TV",
            "display_priority": 28
          }
        ]
      },
      "KE": {
        "link": "https://www.themoviedb.org/movie/26317/watch?locale=KE",
        "free": [
          {
            "logo_path": "/g2IaWyo6jCY0rIFjb4qgZ0bSmm3.jpg",
            "provider_id": 2285,
            "provider_name": "JustWatch TV",
            "display_priority": 15
          }
        ]
      },
      "KR": {
        "link": "https://www.themoviedb.org/movie/26317/watch?locale=KR",
        "flatrate": [
          {
            "logo_path": "/eKVmLFHW5PeNhuR7Nedd8OIxW2M.jpg",
            "provider_id": 100,
            "provider_name": "GuideDoc",
            "display_priority": 7
          }
        ],
        "free": [
          {
            "logo_path": "/g2IaWyo6jCY0rIFjb4qgZ0bSmm3.jpg",
            "provider_id": 2285,
            "provider_name": "JustWatch TV",
            "display_priority": 28
          }
        ]
      },
      "KW": {
        "link": "https://www.themoviedb.org/movie/26317/watch?locale=KW",
        "free": [
          {
            "logo_path": "/g2IaWyo6jCY0rIFjb4qgZ0bSmm3.jpg",
            "provider_id": 2285,
            "provider_name": "JustWatch TV",
            "display_priority": 30
          }
        ]
      },
      "LB": {
        "link": "https://www.themoviedb.org/movie/26317/watch?locale=LB",
        "free": [
          {
            "logo_path": "/g2IaWyo6jCY0rIFjb4qgZ0bSmm3.jpg",
            "provider_id": 2285,
            "provider_name": "JustWatch TV",
            "display_priority": 28
          }
        ]
      },
      "LC": {
        "link": "https://www.themoviedb.org/movie/26317/watch?locale=LC",
        "free": [
          {
            "logo_path": "/g2IaWyo6jCY0rIFjb4qgZ0bSmm3.jpg",
            "provider_id": 2285,
            "provider_name": "JustWatch TV",
            "display_priority": 13
          }
        ]
      },
      "LI": {
        "link": "https://www.themoviedb.org/movie/26317/watch?locale=LI",
        "free": [
          {
            "logo_path": "/g2IaWyo6jCY0rIFjb4qgZ0bSmm3.jpg",
            "provider_id": 2285,
            "provider_name": "JustWatch TV",
            "display_priority": 31
          }
        ]
      },
      "LT": {
        "link": "https://www.themoviedb.org/movie/26317/watch?locale=LT",
        "free": [
          {
            "logo_path": "/g2IaWyo6jCY0rIFjb4qgZ0bSmm3.jpg",
            "provider_id": 2285,
            "provider_name": "JustWatch TV",
            "display_priority": 27
          }
        ],
        "flatrate": [
          {
            "logo_path": "/eKVmLFHW5PeNhuR7Nedd8OIxW2M.jpg",
            "provider_id": 100,
            "provider_name": "GuideDoc",
            "display_priority": 4
          }
        ]
      },
      "LU": {
        "link": "https://www.themoviedb.org/movie/26317/watch?locale=LU",
        "free": [
          {
            "logo_path": "/g2IaWyo6jCY0rIFjb4qgZ0bSmm3.jpg",
            "provider_id": 2285,
            "provider_name": "JustWatch TV",
            "display_priority": 14
          }
        ]
      },
      "LV": {
        "link": "https://www.themoviedb.org/movie/26317/watch?locale=LV",
        "flatrate": [
          {
            "logo_path": "/eKVmLFHW5PeNhuR7Nedd8OIxW2M.jpg",
            "provider_id": 100,
            "provider_name": "GuideDoc",
            "display_priority": 4
          }
        ],
        "free": [
          {
            "logo_path": "/g2IaWyo6jCY0rIFjb4qgZ0bSmm3.jpg",
            "provider_id": 2285,
            "provider_name": "JustWatch TV",
            "display_priority": 26
          }
        ]
      },
      "LY": {
        "link": "https://www.themoviedb.org/movie/26317/watch?locale=LY",
        "free": [
          {
            "logo_path": "/g2IaWyo6jCY0rIFjb4qgZ0bSmm3.jpg",
            "provider_id": 2285,
            "provider_name": "JustWatch TV",
            "display_priority": 28
          }
        ]
      },
      "MA": {
        "link": "https://www.themoviedb.org/movie/26317/watch?locale=MA",
        "free": [
          {
            "logo_path": "/g2IaWyo6jCY0rIFjb4qgZ0bSmm3.jpg",
            "provider_id": 2285,
            "provider_name": "JustWatch TV",
            "display_priority": 27
          }
        ]
      },
      "MC": {
        "link": "https://www.themoviedb.org/movie/26317/watch?locale=MC",
        "free": [
          {
            "logo_path": "/g2IaWyo6jCY0rIFjb4qgZ0bSmm3.jpg",
            "provider_id": 2285,
            "provider_name": "JustWatch TV",
            "display_priority": 26
          }
        ]
      },
      "MD": {
        "link": "https://www.themoviedb.org/movie/26317/watch?locale=MD",
        "free": [
          {
            "logo_path": "/g2IaWyo6jCY0rIFjb4qgZ0bSmm3.jpg",
            "provider_id": 2285,
            "provider_name": "JustWatch TV",
            "display_priority": 26
          }
        ]
      },
      "ME": {
        "link": "https://www.themoviedb.org/movie/26317/watch?locale=ME",
        "free": [
          {
            "logo_path": "/g2IaWyo6jCY0rIFjb4qgZ0bSmm3.jpg",
            "provider_id": 2285,
            "provider_name": "JustWatch TV",
            "display_priority": 7
          }
        ]
      },
      "MG": {
        "link": "https://www.themoviedb.org/movie/26317/watch?locale=MG",
        "free": [
          {
            "logo_path": "/g2IaWyo6jCY0rIFjb4qgZ0bSmm3.jpg",
            "provider_id": 2285,
            "provider_name": "JustWatch TV",
            "display_priority": 5
          }
        ]
      },
      "MK": {
        "link": "https://www.themoviedb.org/movie/26317/watch?locale=MK",
        "free": [
          {
            "logo_path": "/g2IaWyo6jCY0rIFjb4qgZ0bSmm3.jpg",
            "provider_id": 2285,
            "provider_name": "JustWatch TV",
            "display_priority": 27
          }
        ]
      },
      "ML": {
        "link": "https://www.themoviedb.org/movie/26317/watch?locale=ML",
        "free": [
          {
            "logo_path": "/g2IaWyo6jCY0rIFjb4qgZ0bSmm3.jpg",
            "provider_id": 2285,
            "provider_name": "JustWatch TV",
            "display_priority": 6
          }
        ]
      },
      "MT": {
        "link": "https://www.themoviedb.org/movie/26317/watch?locale=MT",
        "free": [
          {
            "logo_path": "/g2IaWyo6jCY0rIFjb4qgZ0bSmm3.jpg",
            "provider_id": 2285,
            "provider_name": "JustWatch TV",
            "display_priority": 25
          }
        ]
      },
      "MU": {
        "link": "https://www.themoviedb.org/movie/26317/watch?locale=MU",
        "free": [
          {
            "logo_path": "/g2IaWyo6jCY0rIFjb4qgZ0bSmm3.jpg",
            "provider_id": 2285,
            "provider_name": "JustWatch TV",
            "display_priority": 15
          }
        ]
      },
      "MW": {
        "link": "https://www.themoviedb.org/movie/26317/watch?locale=MW",
        "free": [
          {
            "logo_path": "/g2IaWyo6jCY0rIFjb4qgZ0bSmm3.jpg",
            "provider_id": 2285,
            "provider_name": "JustWatch TV",
            "display_priority": 3
          }
        ]
      },
      "MX": {
        "link": "https://www.themoviedb.org/movie/26317/watch?locale=MX",
        "flatrate": [
          {
            "logo_path": "/eKVmLFHW5PeNhuR7Nedd8OIxW2M.jpg",
            "provider_id": 100,
            "provider_name": "GuideDoc",
            "display_priority": 14
          }
        ],
        "free": [
          {
            "logo_path": "/g2IaWyo6jCY0rIFjb4qgZ0bSmm3.jpg",
            "provider_id": 2285,
            "provider_name": "JustWatch TV",
            "display_priority": 61
          }
        ]
      },
      "MY": {
        "link": "https://www.themoviedb.org/movie/26317/watch?locale=MY",
        "free": [
          {
            "logo_path": "/g2IaWyo6jCY0rIFjb4qgZ0bSmm3.jpg",
            "provider_id": 2285,
            "provider_name": "JustWatch TV",
            "display_priority": 29
          }
        ]
      },
      "MZ": {
        "link": "https://www.themoviedb.org/movie/26317/watch?locale=MZ",
        "free": [
          {
            "logo_path": "/g2IaWyo6jCY0rIFjb4qgZ0bSmm3.jpg",
            "provider_id": 2285,
            "provider_name": "JustWatch TV",
            "display_priority": 17
          }
        ]
      },
      "NE": {
        "link": "https://www.themoviedb.org/movie/26317/watch?locale=NE",
        "free": [
          {
            "logo_path": "/g2IaWyo6jCY0rIFjb4qgZ0bSmm3.jpg",
            "provider_id": 2285,
            "provider_name": "JustWatch TV",
            "display_priority": 26
          }
        ]
      },
      "NG": {
        "link": "https://www.themoviedb.org/movie/26317/watch?locale=NG",
        "free": [
          {
            "logo_path": "/g2IaWyo6jCY0rIFjb4qgZ0bSmm3.jpg",
            "provider_id": 2285,
            "provider_name": "JustWatch TV",
            "display_priority": 29
          }
        ]
      },
      "NI": {
        "link": "https://www.themoviedb.org/movie/26317/watch?locale=NI",
        "free": [
          {
            "logo_path": "/g2IaWyo6jCY0rIFjb4qgZ0bSmm3.jpg",
            "provider_id": 2285,
            "provider_name": "JustWatch TV",
            "display_priority": 15
          }
        ]
      },
      "NL": {
        "link": "https://www.themoviedb.org/movie/26317/watch?locale=NL",
        "free": [
          {
            "logo_path": "/g2IaWyo6jCY0rIFjb4qgZ0bSmm3.jpg",
            "provider_id": 2285,
            "provider_name": "JustWatch TV",
            "display_priority": 53
          }
        ],
        "flatrate": [
          {
            "logo_path": "/eKVmLFHW5PeNhuR7Nedd8OIxW2M.jpg",
            "provider_id": 100,
            "provider_name": "GuideDoc",
            "display_priority": 16
          }
        ]
      },
      "NO": {
        "link": "https://www.themoviedb.org/movie/26317/watch?locale=NO",
        "flatrate": [
          {
            "logo_path": "/eKVmLFHW5PeNhuR7Nedd8OIxW2M.jpg",
            "provider_id": 100,
            "provider_name": "GuideDoc",
            "display_priority": 9
          }
        ],
        "free": [
          {
            "logo_path": "/g2IaWyo6jCY0rIFjb4qgZ0bSmm3.jpg",
            "provider_id": 2285,
            "provider_name": "JustWatch TV",
            "display_priority": 41
          }
        ]
      },
      "NZ": {
        "link": "https://www.themoviedb.org/movie/26317/watch?locale=NZ",
        "free": [
          {
            "logo_path": "/g2IaWyo6jCY0rIFjb4qgZ0bSmm3.jpg",
            "provider_id": 2285,
            "provider_name": "JustWatch TV",
            "display_priority": 4
          }
        ],
        "flatrate": [
          {
            "logo_path": "/eKVmLFHW5PeNhuR7Nedd8OIxW2M.jpg",
            "provider_id": 100,
            "provider_name": "GuideDoc",
            "display_priority": 12
          }
        ]
      },
      "OM": {
        "link": "https://www.themoviedb.org/movie/26317/watch?locale=OM",
        "free": [
          {
            "logo_path": "/g2IaWyo6jCY0rIFjb4qgZ0bSmm3.jpg",
            "provider_id": 2285,
            "provider_name": "JustWatch TV",
            "display_priority": 29
          }
        ]
      },
      "PA": {
        "link": "https://www.themoviedb.org/movie/26317/watch?locale=PA",
        "free": [
          {
            "logo_path": "/g2IaWyo6jCY0rIFjb4qgZ0bSmm3.jpg",
            "provider_id": 2285,
            "provider_name": "JustWatch TV",
            "display_priority": 32
          }
        ]
      },
      "PE": {
        "link": "https://www.themoviedb.org/movie/26317/watch?locale=PE",
        "free": [
          {
            "logo_path": "/g2IaWyo6jCY0rIFjb4qgZ0bSmm3.jpg",
            "provider_id": 2285,
            "provider_name": "JustWatch TV",
            "display_priority": 33
          }
        ]
      },
      "PF": {
        "link": "https://www.themoviedb.org/movie/26317/watch?locale=PF",
        "free": [
          {
            "logo_path": "/g2IaWyo6jCY0rIFjb4qgZ0bSmm3.jpg",
            "provider_id": 2285,
            "provider_name": "JustWatch TV",
            "display_priority": 11
          }
        ]
      },
      "PG": {
        "link": "https://www.themoviedb.org/movie/26317/watch?locale=PG",
        "free": [
          {
            "logo_path": "/g2IaWyo6jCY0rIFjb4qgZ0bSmm3.jpg",
            "provider_id": 2285,
            "provider_name": "JustWatch TV",
            "display_priority": 5
          }
        ]
      },
      "PH": {
        "link": "https://www.themoviedb.org/movie/26317/watch?locale=PH",
        "free": [
          {
            "logo_path": "/g2IaWyo6jCY0rIFjb4qgZ0bSmm3.jpg",
            "provider_id": 2285,
            "provider_name": "JustWatch TV",
            "display_priority": 31
          }
        ]
      },
      "PK": {
        "link": "https://www.themoviedb.org/movie/26317/watch?locale=PK",
        "free": [
          {
            "logo_path": "/g2IaWyo6jCY0rIFjb4qgZ0bSmm3.jpg",
            "provider_id": 2285,
            "provider_name": "JustWatch TV",
            "display_priority": 8
          }
        ]
      },
      "PL": {
        "link": "https://www.themoviedb.org/movie/26317/watch?locale=PL",
        "flatrate": [
          {
            "logo_path": "/eKVmLFHW5PeNhuR7Nedd8OIxW2M.jpg",
            "provider_id": 100,
            "provider_name": "GuideDoc",
            "display_priority": 11
          }
        ],
        "free": [
          {
            "logo_path": "/g2IaWyo6jCY0rIFjb4qgZ0bSmm3.jpg",
            "provider_id": 2285,
            "provider_name": "JustWatch TV",
            "display_priority": 43
          }
        ]
      },
      "PS": {
        "link": "https://www.themoviedb.org/movie/26317/watch?locale=PS",
        "free": [
          {
            "logo_path": "/g2IaWyo6jCY0rIFjb4qgZ0bSmm3.jpg",
            "provider_id": 2285,
            "provider_name": "JustWatch TV",
            "display_priority": 26
          }
        ]
      },
      "PT": {
        "link": "https://www.themoviedb.org/movie/26317/watch?locale=PT",
        "free": [
          {
            "logo_path": "/g2IaWyo6jCY0rIFjb4qgZ0bSmm3.jpg",
            "provider_id": 2285,
            "provider_name": "JustWatch TV",
            "display_priority": 33
          }
        ]
      },
      "PY": {
        "link": "https://www.themoviedb.org/movie/26317/watch?locale=PY",
        "free": [
          {
            "logo_path": "/g2IaWyo6jCY0rIFjb4qgZ0bSmm3.jpg",
            "provider_id": 2285,
            "provider_name": "JustWatch TV",
            "display_priority": 31
          }
        ]
      },
      "QA": {
        "link": "https://www.themoviedb.org/movie/26317/watch?locale=QA",
        "free": [
          {
            "logo_path": "/g2IaWyo6jCY0rIFjb4qgZ0bSmm3.jpg",
            "provider_id": 2285,
            "provider_name": "JustWatch TV",
            "display_priority": 28
          }
        ]
      },
      "RO": {
        "link": "https://www.themoviedb.org/movie/26317/watch?locale=RO",
        "free": [
          {
            "logo_path": "/g2IaWyo6jCY0rIFjb4qgZ0bSmm3.jpg",
            "provider_id": 2285,
            "provider_name": "JustWatch TV",
            "display_priority": 24
          }
        ]
      },
      "RS": {
        "link": "https://www.themoviedb.org/movie/26317/watch?locale=RS",
        "free": [
          {
            "logo_path": "/g2IaWyo6jCY0rIFjb4qgZ0bSmm3.jpg",
            "provider_id": 2285,
            "provider_name": "JustWatch TV",
            "display_priority": 29
          }
        ]
      },
      "RU": {
        "link": "https://www.themoviedb.org/movie/26317/watch?locale=RU",
        "flatrate": [
          {
            "logo_path": "/eKVmLFHW5PeNhuR7Nedd8OIxW2M.jpg",
            "provider_id": 100,
            "provider_name": "GuideDoc",
            "display_priority": 5
          }
        ],
        "free": [
          {
            "logo_path": "/g2IaWyo6jCY0rIFjb4qgZ0bSmm3.jpg",
            "provider_id": 2285,
            "provider_name": "JustWatch TV",
            "display_priority": 29
          }
        ]
      },
      "SA": {
        "link": "https://www.themoviedb.org/movie/26317/watch?locale=SA",
        "free": [
          {
            "logo_path": "/g2IaWyo6jCY0rIFjb4qgZ0bSmm3.jpg",
            "provider_id": 2285,
            "provider_name": "JustWatch TV",
            "display_priority": 30
          }
        ]
      },
      "SC": {
        "link": "https://www.themoviedb.org/movie/26317/watch?locale=SC",
        "free": [
          {
            "logo_path": "/g2IaWyo6jCY0rIFjb4qgZ0bSmm3.jpg",
            "provider_id": 2285,
            "provider_name": "JustWatch TV",
            "display_priority": 14
          }
        ]
      },
      "SE": {
        "link": "https://www.themoviedb.org/movie/26317/watch?locale=SE",
        "flatrate": [
          {
            "logo_path": "/eKVmLFHW5PeNhuR7Nedd8OIxW2M.jpg",
            "provider_id": 100,
            "provider_name": "GuideDoc",
            "display_priority": 9
          },
          {
            "logo_path": "/4SJW6thrCvN6ya2hO6naksfRZDF.jpg",
            "provider_id": 287,
            "provider_name": "BFI Player Amazon Channel",
            "display_priority": 59
          }
        ],
        "free": [
          {
            "logo_path": "/g2IaWyo6jCY0rIFjb4qgZ0bSmm3.jpg",
            "provider_id": 2285,
            "provider_name": "JustWatch TV",
            "display_priority": 45
          }
        ]
      },
      "SG": {
        "link": "https://www.themoviedb.org/movie/26317/watch?locale=SG",
        "free": [
          {
            "logo_path": "/g2IaWyo6jCY0rIFjb4qgZ0bSmm3.jpg",
            "provider_id": 2285,
            "provider_name": "JustWatch TV",
            "display_priority": 30
          }
        ],
        "flatrate": [
          {
            "logo_path": "/eKVmLFHW5PeNhuR7Nedd8OIxW2M.jpg",
            "provider_id": 100,
            "provider_name": "GuideDoc",
            "display_priority": 8
          }
        ]
      },
      "SI": {
        "link": "https://www.themoviedb.org/movie/26317/watch?locale=SI",
        "free": [
          {
            "logo_path": "/g2IaWyo6jCY0rIFjb4qgZ0bSmm3.jpg",
            "provider_id": 2285,
            "provider_name": "JustWatch TV",
            "display_priority": 29
          }
        ]
      },
      "SK": {
        "link": "https://www.themoviedb.org/movie/26317/watch?locale=SK",
        "free": [
          {
            "logo_path": "/g2IaWyo6jCY0rIFjb4qgZ0bSmm3.jpg",
            "provider_id": 2285,
            "provider_name": "JustWatch TV",
            "display_priority": 38
          }
        ],
        "flatrate": [
          {
            "logo_path": "/eKVmLFHW5PeNhuR7Nedd8OIxW2M.jpg",
            "provider_id": 100,
            "provider_name": "GuideDoc",
            "display_priority": 9
          },
          {
            "logo_path": "/hsuv1uc7SUr9YjCXRlLQNELt4UU.jpg",
            "provider_id": 628,
            "provider_name": "Edisonline",
            "display_priority": 24
          }
        ]
      },
      "SM": {
        "link": "https://www.themoviedb.org/movie/26317/watch?locale=SM",
        "free": [
          {
            "logo_path": "/g2IaWyo6jCY0rIFjb4qgZ0bSmm3.jpg",
            "provider_id": 2285,
            "provider_name": "JustWatch TV",
            "display_priority": 27
          }
        ]
      },
      "SN": {
        "link": "https://www.themoviedb.org/movie/26317/watch?locale=SN",
        "free": [
          {
            "logo_path": "/g2IaWyo6jCY0rIFjb4qgZ0bSmm3.jpg",
            "provider_id": 2285,
            "provider_name": "JustWatch TV",
            "display_priority": 14
          }
        ]
      },
      "SV": {
        "link": "https://www.themoviedb.org/movie/26317/watch?locale=SV",
        "free": [
          {
            "logo_path": "/g2IaWyo6jCY0rIFjb4qgZ0bSmm3.jpg",
            "provider_id": 2285,
            "provider_name": "JustWatch TV",
            "display_priority": 32
          }
        ]
      },
      "TC": {
        "link": "https://www.themoviedb.org/movie/26317/watch?locale=TC",
        "free": [
          {
            "logo_path": "/g2IaWyo6jCY0rIFjb4qgZ0bSmm3.jpg",
            "provider_id": 2285,
            "provider_name": "JustWatch TV",
            "display_priority": 12
          }
        ]
      },
      "TD": {
        "link": "https://www.themoviedb.org/movie/26317/watch?locale=TD",
        "free": [
          {
            "logo_path": "/g2IaWyo6jCY0rIFjb4qgZ0bSmm3.jpg",
            "provider_id": 2285,
            "provider_name": "JustWatch TV",
            "display_priority": 6
          }
        ]
      },
      "TH": {
        "link": "https://www.themoviedb.org/movie/26317/watch?locale=TH",
        "flatrate": [
          {
            "logo_path": "/eKVmLFHW5PeNhuR7Nedd8OIxW2M.jpg",
            "provider_id": 100,
            "provider_name": "GuideDoc",
            "display_priority": 6
          }
        ],
        "free": [
          {
            "logo_path": "/g2IaWyo6jCY0rIFjb4qgZ0bSmm3.jpg",
            "provider_id": 2285,
            "provider_name": "JustWatch TV",
            "display_priority": 29
          }
        ]
      },
      "TN": {
        "link": "https://www.themoviedb.org/movie/26317/watch?locale=TN",
        "free": [
          {
            "logo_path": "/g2IaWyo6jCY0rIFjb4qgZ0bSmm3.jpg",
            "provider_id": 2285,
            "provider_name": "JustWatch TV",
            "display_priority": 28
          }
        ]
      },
      "TR": {
        "link": "https://www.themoviedb.org/movie/26317/watch?locale=TR",
        "free": [
          {
            "logo_path": "/g2IaWyo6jCY0rIFjb4qgZ0bSmm3.jpg",
            "provider_id": 2285,
            "provider_name": "JustWatch TV",
            "display_priority": 26
          }
        ]
      },
      "TT": {
        "link": "https://www.themoviedb.org/movie/26317/watch?locale=TT",
        "free": [
          {
            "logo_path": "/g2IaWyo6jCY0rIFjb4qgZ0bSmm3.jpg",
            "provider_id": 2285,
            "provider_name": "JustWatch TV",
            "display_priority": 14
          }
        ]
      },
      "TW": {
        "link": "https://www.themoviedb.org/movie/26317/watch?locale=TW",
        "free": [
          {
            "logo_path": "/g2IaWyo6jCY0rIFjb4qgZ0bSmm3.jpg",
            "provider_id": 2285,
            "provider_name": "JustWatch TV",
            "display_priority": 37
          }
        ]
      },
      "TZ": {
        "link": "https://www.themoviedb.org/movie/26317/watch?locale=TZ",
        "free": [
          {
            "logo_path": "/g2IaWyo6jCY0rIFjb4qgZ0bSmm3.jpg",
            "provider_id": 2285,
            "provider_name": "JustWatch TV",
            "display_priority": 31
          }
        ],
        "flatrate": [
          {
            "logo_path": "/eKVmLFHW5PeNhuR7Nedd8OIxW2M.jpg",
            "provider_id": 100,
            "provider_name": "GuideDoc",
            "display_priority": 12
          }
        ]
      },
      "UA": {
        "link": "https://www.themoviedb.org/movie/26317/watch?locale=UA",
        "free": [
          {
            "logo_path": "/g2IaWyo6jCY0rIFjb4qgZ0bSmm3.jpg",
            "provider_id": 2285,
            "provider_name": "JustWatch TV",
            "display_priority": 8
          }
        ]
      },
      "UG": {
        "link": "https://www.themoviedb.org/movie/26317/watch?locale=UG",
        "free": [
          {
            "logo_path": "/g2IaWyo6jCY0rIFjb4qgZ0bSmm3.jpg",
            "provider_id": 2285,
            "provider_name": "JustWatch TV",
            "display_priority": 16
          }
        ]
      },
      "US": {
        "link": "https://www.themoviedb.org/movie/26317/watch?locale=US",
        "buy": [
          {
            "logo_path": "/qR6FKvnPBx2O37FDg8PNM7efwF3.jpg",
            "provider_id": 10,
            "provider_name": "Amazon Video",
            "display_priority": 6
          },
          {
            "logo_path": "/SPnB1qiCkYfirS2it3hZORwGVn.jpg",
            "provider_id": 2,
            "provider_name": "Apple TV Store",
            "display_priority": 7
          },
          {
            "logo_path": "/19fkcOz0xeUgCVW8tO85uOYnYK9.jpg",
            "provider_id": 7,
            "provider_name": "Fandango At Home",
            "display_priority": 35
          }
        ],
        "flatrate": [
          {
            "logo_path": "/eKVmLFHW5PeNhuR7Nedd8OIxW2M.jpg",
            "provider_id": 100,
            "provider_name": "GuideDoc",
            "display_priority": 58
          }
        ],
        "free": [
          {
            "logo_path": "/rcBwnERpNfPfWB5DaSTyEMCZbCA.jpg",
            "provider_id": 191,
            "provider_name": "Kanopy",
            "display_priority": 33
          },
          {
            "logo_path": "/g2IaWyo6jCY0rIFjb4qgZ0bSmm3.jpg",
            "provider_id": 2285,
            "provider_name": "JustWatch TV",
            "display_priority": 42
          },
          {
            "logo_path": "/8G7qvHF7hdmXpfxxqtF1WT9ib68.jpg",
            "provider_id": 2308,
            "provider_name": "Darkroom",
            "display_priority": 137
          }
        ],
        "ads": [
          {
            "logo_path": "/19fkcOz0xeUgCVW8tO85uOYnYK9.jpg",
            "provider_id": 332,
            "provider_name": "Fandango at Home Free",
            "display_priority": 38
          }
        ],
        "rent": [
          {
            "logo_path": "/qR6FKvnPBx2O37FDg8PNM7efwF3.jpg",
            "provider_id": 10,
            "provider_name": "Amazon Video",
            "display_priority": 6
          },
          {
            "logo_path": "/SPnB1qiCkYfirS2it3hZORwGVn.jpg",
            "provider_id": 2,
            "provider_name": "Apple TV Store",
            "display_priority": 7
          },
          {
            "logo_path": "/19fkcOz0xeUgCVW8tO85uOYnYK9.jpg",
            "provider_id": 7,
            "provider_name": "Fandango At Home",
            "display_priority": 35
          }
        ]
      },
      "UY": {
        "link": "https://www.themoviedb.org/movie/26317/watch?locale=UY",
        "free": [
          {
            "logo_path": "/g2IaWyo6jCY0rIFjb4qgZ0bSmm3.jpg",
            "provider_id": 2285,
            "provider_name": "JustWatch TV",
            "display_priority": 31
          }
        ]
      },
      "VA": {
        "link": "https://www.themoviedb.org/movie/26317/watch?locale=VA",
        "free": [
          {
            "logo_path": "/g2IaWyo6jCY0rIFjb4qgZ0bSmm3.jpg",
            "provider_id": 2285,
            "provider_name": "JustWatch TV",
            "display_priority": 7
          }
        ]
      },
      "VE": {
        "link": "https://www.themoviedb.org/movie/26317/watch?locale=VE",
        "free": [
          {
            "logo_path": "/g2IaWyo6jCY0rIFjb4qgZ0bSmm3.jpg",
            "provider_id": 2285,
            "provider_name": "JustWatch TV",
            "display_priority": 29
          }
        ]
      },
      "XK": {
        "link": "https://www.themoviedb.org/movie/26317/watch?locale=XK",
        "free": [
          {
            "logo_path": "/g2IaWyo6jCY0rIFjb4qgZ0bSmm3.jpg",
            "provider_id": 2285,
            "provider_name": "JustWatch TV",
            "display_priority": 6
          }
        ]
      },
      "YE": {
        "link": "https://www.themoviedb.org/movie/26317/watch?locale=YE",
        "free": [
          {
            "logo_path": "/g2IaWyo6jCY0rIFjb4qgZ0bSmm3.jpg",
            "provider_id": 2285,
            "provider_name": "JustWatch TV",
            "display_priority": 27
          }
        ]
      },
      "ZA": {
        "link": "https://www.themoviedb.org/movie/26317/watch?locale=ZA",
        "free": [
          {
            "logo_path": "/g2IaWyo6jCY0rIFjb4qgZ0bSmm3.jpg",
            "provider_id": 2285,
            "provider_name": "JustWatch TV",
            "display_priority": 28
          }
        ]
      },
      "ZM": {
        "link": "https://www.themoviedb.org/movie/26317/watch?locale=ZM",
        "free": [
          {
            "logo_path": "/g2IaWyo6jCY0rIFjb4qgZ0bSmm3.jpg",
            "provider_id": 2285,
            "provider_name": "JustWatch TV",
            "display_priority": 14
          }
        ]
      },
      "ZW": {
        "link": "https://www.themoviedb.org/movie/26317/watch?locale=ZW",
        "free": [
          {
            "logo_path": "/g2IaWyo6jCY0rIFjb4qgZ0bSmm3.jpg",
            "provider_id": 2285,
            "provider_name": "JustWatch TV",
            "display_priority": 6
          }
        ]
      }
    }
  }
}