{
  "id": "person_cho-yeo-jeong",
  "name": "Cho Yeo-jeong",
  "biography": "Cho Yeo-jeong (조여정) is a South Korean actress. Born on February 10, 1981, she began her career as a model in 1997 at the age of 16 and launched her acting career two years later. She is best known for her roles in the provocative period films “The Servant” (2010) and “The Concubine” (2012) and the television dramas “I Need Romance” (2011), “Haeundae Lovers” (2012), “Divorce Lawyer in Love” (2015) and “Perfect Wife” (2017).",
  "birth_year": 1981,
  "death_year": null,
  "nationality": [
    "Seoul, South Korea"
  ],
  "profile_path": "/5MgWM8pkUiYkj9MEaEpO0Ir1FD9.jpg",
  "roles": [
    "cast"
  ],
  "works": [],
  "ids": {
    "tmdb": 556435,
    "imdb": "nm1856097"
  }
}