{
  "id": "work_the-night-of-the-hunter_1955",
  "type": "film",
  "title": "The Night of the Hunter",
  "original_title": "The Night of the Hunter",
  "year": 1955,
  "duration_min": 93,
  "synopsis": "In Depression-era West Virginia, a serial-killing preacher hunts two young children who know the whereabouts of a stash of money.",
  "tagline": "It\u2019s a hard world for little things.",
  "countries": [
    "US"
  ],
  "languages": [
    "en"
  ],
  "ids": {
    "tmdb": 3112,
    "imdb": "tt0048424"
  },
  "genres": [
    "Crime",
    "Drama",
    "Thriller"
  ],
  "tmdb_popularity": 4.4504,
  "media": {
    "poster_path": "/rBka0nFWiHxabHRLr0KfIA8Yiaq.jpg",
    "backdrop_path": "/ngh5pnvXPceZYdeKZqO4OYS9VHF.jpg",
    "trailer_key": "GAxs6tChiKo"
  },
  "where_to_watch": {
    "AE": {
      "rent": [
        "Apple TV Store"
      ],
      "buy": [
        "Apple TV Store"
      ]
    },
    "AO": {
      "rent": [
        "Google Play Movies"
      ],
      "buy": [
        "Google Play Movies"
      ]
    },
    "AR": {
      "rent": [
        "Apple TV Store",
        "Google Play Movies"
      ],
      "buy": [
        "Apple TV Store",
        "Google Play Movies"
      ]
    },
    "AT": {
      "flatrate": [
        "MGM Plus Amazon Channel"
      ],
      "rent": [
        "Amazon Video",
        "Apple TV Store"
      ],
      "buy": [
        "Amazon Video",
        "Apple TV Store"
      ]
    },
    "AU": {
      "flatrate": [
        "MGM Amazon Channel"
      ],
      "rent": [
        "Apple TV Store",
        "Amazon Video"
      ],
      "buy": [
        "Apple TV Store",
        "Amazon Video"
      ]
    },
    "AZ": {
      "rent": [
        "Google Play Movies"
      ],
      "buy": [
        "Google Play Movies"
      ]
    },
    "BE": {
      "flatrate": [
        "MGM Plus Amazon Channel"
      ],
      "rent": [
        "Apple TV Store",
        "Google Play Movies",
        "Amazon Video"
      ],
      "buy": [
        "Apple TV Store",
        "Google Play Movies",
        "Amazon Video"
      ]
    },
    "BF": {
      "rent": [
        "Google Play Movies"
      ],
      "buy": [
        "Google Play Movies"
      ]
    },
    "BG": {
      "rent": [
        "Apple TV Store"
      ],
      "buy": [
        "Apple TV Store"
      ]
    },
    "BO": {
      "rent": [
        "Apple TV Store",
        "Google Play Movies"
      ],
      "buy": [
        "Apple TV Store",
        "Google Play Movies"
      ]
    },
    "BR": {
      "flatrate": [
        "Belas Artes \u00e0 La Carte",
        "MGM+ Apple TV Channel",
        "MGM Plus Amazon Channel"
      ],
      "rent": [
        "Apple TV Store",
        "Amazon Video"
      ],
      "buy": [
        "Apple TV Store",
        "Amazon Video"
      ]
    },
    "BY": {
      "rent": [
        "Apple TV Store",
        "Google Play Movies"
      ],
      "buy": [
        "Apple TV Store",
        "Google Play Movies"
      ]
    },
    "BZ": {
      "rent": [
        "Apple TV Store",
        "Google Play Movies"
      ],
      "buy": [
        "Apple TV Store",
        "Google Play Movies"
      ]
    },
    "CA": {
      "flatrate": [
        "MGM Amazon Channel"
      ],
      "rent": [
        "Apple TV Store",
        "Google Play Movies",
        "YouTube",
        "Amazon Video"
      ],
      "buy": [
        "Apple TV Store",
        "Google Play Movies",
        "YouTube",
        "Amazon Video"
      ]
    },
    "CH": {
      "rent": [
        "Apple TV Store",
        "Google Play Movies",
        "Amazon Video"
      ],
      "buy": [
        "Apple TV Store",
        "Google Play Movies",
        "Amazon Video"
      ]
    },
    "CL": {
      "flatrate": [
        "MGM+ Apple TV Channel",
        "MGM Plus Amazon Channel"
      ],
      "rent": [
        "Apple TV Store",
        "Google Play Movies",
        "Amazon Video"
      ],
      "buy": [
        "Apple TV Store",
        "Google Play Movies",
        "Amazon Video"
      ]
    },
    "CO": {
      "flatrate": [
        "MGM+ Apple TV Channel",
        "MGM Plus Amazon Channel"
      ],
      "rent": [
        "Google Play Movies",
        "Apple TV Store",
        "Amazon Video"
      ],
      "buy": [
        "Google Play Movies",
        "Apple TV Store",
        "Amazon Video"
      ]
    },
    "CR": {
      "rent": [
        "Apple TV Store",
        "Google Play Movies"
      ],
      "buy": [
        "Apple TV Store",
        "Google Play Movies"
      ]
    },
    "CV": {
      "rent": [
        "Apple TV Store"
      ],
      "buy": [
        "Apple TV Store"
      ]
    },
    "CY": {
      "rent": [
        "Apple TV Store",
        "Google Play Movies"
      ],
      "buy": [
        "Apple TV Store",
        "Google Play Movies"
      ]
    },
    "CZ": {
      "rent": [
        "Apple TV Store",
        "Google Play Movies",
        "Amazon Video"
      ],
      "buy": [
        "Apple TV Store",
        "Google Play Movies",
        "Amazon Video"
      ]
    },
    "DE": {
      "flatrate": [
        "MGM Plus Amazon Channel"
      ],
      "rent": [
        "Apple TV Store",
        "Amazon Video"
      ],
      "buy": [
        "Apple TV Store",
        "Amazon Video"
      ]
    },
    "DK": {
      "rent": [
        "Apple TV Store",
        "Google Play Movies",
        "SF Anytime",
        "Amazon Video"
      ],
      "buy": [
        "Apple TV Store",
        "Google Play Movies",
        "SF Anytime",
        "Amazon Video"
      ]
    },
    "EC": {
      "rent": [
        "Apple TV Store",
        "Google Play Movies"
      ],
      "buy": [
        "Apple TV Store",
        "Google Play Movies"
      ]
    },
    "EE": {
      "rent": [
        "Apple TV Store"
      ],
      "buy": [
        "Apple TV Store"
      ]
    },
    "EG": {
      "rent": [
        "Apple TV Store"
      ],
      "buy": [
        "Apple TV Store"
      ]
    },
    "ES": {
      "flatrate": [
        "Filmin",
        "MGM Plus Amazon Channel"
      ],
      "rent": [
        "Apple TV Store",
        "Amazon Video"
      ],
      "buy": [
        "Apple TV Store",
        "Amazon Video"
      ]
    },
    "FI": {
      "flatrate": [
        "MGM Amazon Channel"
      ],
      "rent": [
        "Apple TV Store",
        "Google Play Movies",
        "SF Anytime",
        "Amazon Video"
      ],
      "buy": [
        "Apple TV Store",
        "Google Play Movies",
        "SF Anytime",
        "Amazon Video"
      ]
    },
    "FR": {
      "flatrate": [
        "MGM Amazon Channel"
      ],
      "rent": [
        "Apple TV Store",
        "Canal VOD",
        "Orange VOD",
        "Amazon Video",
        "Path\u00e9 Home"
      ],
      "buy": [
        "Apple TV Store",
        "Canal VOD",
        "Orange VOD",
        "Amazon Video",
        "Path\u00e9 Home"
      ]
    },
    "GB": {
      "flatrate": [
        "MGM Plus Amazon Channel"
      ],
      "rent": [
        "Apple TV Store",
        "Amazon Video",
        "Google Play Movies",
        "YouTube"
      ],
      "buy": [
        "Apple TV Store",
        "Amazon Video",
        "Google Play Movies",
        "Sky Store",
        "YouTube"
      ]
    },
    "GG": {
      "rent": [
        "Amazon Video"
      ],
      "buy": [
        "Amazon Video"
      ]
    },
    "GH": {
      "rent": [
        "Apple TV Store"
      ],
      "buy": [
        "Apple TV Store"
      ]
    },
    "GR": {
      "rent": [
        "Apple TV Store",
        "Google Play Movies"
      ],
      "buy": [
        "Apple TV Store",
        "Google Play Movies"
      ]
    },
    "GT": {
      "rent": [
        "Apple TV Store",
        "Google Play Movies"
      ],
      "buy": [
        "Apple TV Store",
        "Google Play Movies"
      ]
    },
    "HK": {
      "rent": [
        "Apple TV Store"
      ],
      "buy": [
        "Apple TV Store"
      ]
    },
    "HN": {
      "rent": [
        "Apple TV Store",
        "Google Play Movies"
      ],
      "buy": [
        "Apple TV Store",
        "Google Play Movies"
      ]
    },
    "HR": {
      "rent": [
        "Google Play Movies"
      ],
      "buy": [
        "Google Play Movies"
      ]
    },
    "HU": {
      "rent": [
        "Apple TV Store",
        "Google Play Movies",
        "Amazon Video"
      ],
      "buy": [
        "Apple TV Store",
        "Google Play Movies",
        "Amazon Video"
      ]
    },
    "ID": {
      "rent": [
        "Apple TV Store"
      ],
      "buy": [
        "Apple TV Store"
      ]
    },
    "IE": {
      "rent": [
        "Apple TV Store",
        "Google Play Movies",
        "Amazon Video"
      ],
      "buy": [
        "Apple TV Store",
        "Google Play Movies",
        "Sky Store",
        "Amazon Video"
      ]
    },
    "IL": {
      "rent": [
        "Apple TV Store"
      ],
      "buy": [
        "Apple TV Store"
      ]
    },
    "IN": {
      "flatrate": [
        "MGM Plus Amazon Channel"
      ],
      "rent": [
        "Amazon Video"
      ]
    },
    "IS": {
      "rent": [
        "Google Play Movies"
      ],
      "buy": [
        "Google Play Movies"
      ]
    },
    "IT": {
      "flatrate": [
        "MGM Plus Amazon Channel"
      ],
      "rent": [
        "Apple TV Store",
        "Amazon Video",
        "CHILI"
      ],
      "buy": [
        "Apple TV Store",
        "Amazon Video",
        "CHILI"
      ]
    },
    "JP": {
      "flatrate": [
        "U-NEXT"
      ]
    },
    "KR": {
      "flatrate": [
        "Watcha"
      ],
      "rent": [
        "wavve"
      ]
    },
    "LT": {
      "rent": [
        "Apple TV Store",
        "Google Play Movies"
      ],
      "buy": [
        "Apple TV Store",
        "Google Play Movies"
      ]
    },
    "LU": {
      "rent": [
        "Apple TV Store",
        "Google Play Movies"
      ],
      "buy": [
        "Apple TV Store",
        "Google Play Movies"
      ]
    },
    "LV": {
      "rent": [
        "Apple TV Store",
        "Google Play Movies"
      ],
      "buy": [
        "Apple TV Store",
        "Google Play Movies"
      ]
    },
    "ML": {
      "rent": [
        "Google Play Movies"
      ],
      "buy": [
        "Google Play Movies"
      ]
    },
    "MU": {
      "rent": [
        "Apple TV Store"
      ],
      "buy": [
        "Apple TV Store"
      ]
    },
    "MX": {
      "flatrate": [
        "MGM+ Apple TV Channel",
        "MGM Plus Amazon Channel"
      ],
      "rent": [
        "Apple TV Store",
        "Amazon Video"
      ],
      "buy": [
        "Apple TV Store",
        "Amazon Video"
      ]
    },
    "MY": {
      "rent": [
        "Apple TV Store"
      ],
      "buy": [
        "Apple TV Store"
      ]
    },
    "MZ": {
      "rent": [
        "Apple TV Store"
      ],
      "buy": [
        "Apple TV Store"
      ]
    },
    "NI": {
      "rent": [
        "Apple TV Store",
        "Google Play Movies"
      ],
      "buy": [
        "Apple TV Store",
        "Google Play Movies"
      ]
    },
    "NL": {
      "flatrate": [
        "MGM Plus Amazon Channel"
      ],
      "rent": [
        "Apple TV Store",
        "Google Play Movies",
        "Amazon Video"
      ],
      "buy": [
        "Apple TV Store",
        "Google Play Movies",
        "Amazon Video"
      ]
    },
    "NO": {
      "rent": [
        "Apple TV Store",
        "Google Play Movies",
        "SF Anytime",
        "Amazon Video"
      ],
      "buy": [
        "Apple TV Store",
        "Google Play Movies",
        "SF Anytime",
        "Amazon Video"
      ]
    },
    "NZ": {
      "flatrate": [
        "MGM Plus Amazon Channel"
      ],
      "rent": [
        "Apple TV Store",
        "Google Play Movies",
        "Amazon Video"
      ],
      "buy": [
        "Apple TV Store",
        "Google Play Movies",
        "Amazon Video"
      ]
    },
    "PE": {
      "rent": [
        "Apple TV Store",
        "Google Play Movies"
      ],
      "buy": [
        "Apple TV Store",
        "Google Play Movies"
      ]
    },
    "PG": {
      "rent": [
        "Google Play Movies"
      ],
      "buy": [
        "Google Play Movies"
      ]
    },
    "PH": {
      "rent": [
        "Apple TV Store",
        "Google Play Movies"
      ],
      "buy": [
        "Apple TV Store",
        "Google Play Movies"
      ]
    },
    "PL": {
      "flatrate": [
        "MGM Amazon Channel"
      ],
      "rent": [
        "Apple TV Store",
        "Google Play Movies",
        "YouTube",
        "Amazon Video",
        "CHILI"
      ],
      "buy": [
        "Apple TV Store",
        "Google Play Movies",
        "YouTube",
        "Amazon Video",
        "CHILI"
      ]
    },
    "PT": {
      "rent": [
        "Apple TV Store",
        "Google Play Movies",
        "YouTube",
        "Amazon Video"
      ],
      "buy": [
        "Apple TV Store",
        "Google Play Movies",
        "YouTube",
        "Amazon Video"
      ]
    },
    "PY": {
      "rent": [
        "Apple TV Store",
        "Google Play Movies"
      ],
      "buy": [
        "Apple TV Store",
        "Google Play Movies"
      ]
    },
    "RO": {
      "rent": [
        "Amazon Video"
      ],
      "buy": [
        "Amazon Video"
      ]
    },
    "RU": {
      "rent": [
        "Apple TV Store"
      ],
      "buy": [
        "Apple TV Store"
      ]
    },
    "SA": {
      "rent": [
        "Apple TV Store"
      ],
      "buy": [
        "Apple TV Store"
      ]
    },
    "SE": {
      "flatrate": [
        "MGM Amazon Channel"
      ],
      "rent": [
        "Apple TV Store",
        "Google Play Movies",
        "SF Anytime",
        "Amazon Video"
      ],
      "buy": [
        "Apple TV Store",
        "Google Play Movies",
        "SF Anytime",
        "Amazon Video"
      ]
    },
    "SG": {
      "rent": [
        "Apple TV Store"
      ],
      "buy": [
        "Apple TV Store"
      ]
    },
    "SI": {
      "rent": [
        "Apple TV Store"
      ],
      "buy": [
        "Apple TV Store"
      ]
    },
    "SK": {
      "rent": [
        "Apple TV Store",
        "Google Play Movies"
      ],
      "buy": [
        "Apple TV Store",
        "Google Play Movies"
      ]
    },
    "TH": {
      "rent": [
        "Apple TV Store",
        "Google Play Movies"
      ],
      "buy": [
        "Apple TV Store",
        "Google Play Movies"
      ]
    },
    "TR": {
      "rent": [
        "Google Play Movies"
      ],
      "buy": [
        "Google Play Movies"
      ]
    },
    "TW": {
      "rent": [
        "Apple TV Store"
      ],
      "buy": [
        "Apple TV Store"
      ]
    },
    "TZ": {
      "rent": [
        "Google Play Movies"
      ],
      "buy": [
        "Google Play Movies"
      ]
    },
    "UA": {
      "rent": [
        "Apple TV Store",
        "Google Play Movies"
      ],
      "buy": [
        "Apple TV Store",
        "Google Play Movies"
      ]
    },
    "UG": {
      "rent": [
        "Apple TV Store"
      ],
      "buy": [
        "Apple TV Store"
      ]
    },
    "US": {
      "rent": [
        "Apple TV Store",
        "Google Play Movies",
        "YouTube",
        "Fandango At Home",
        "Spectrum On Demand"
      ],
      "buy": [
        "Apple TV Store",
        "Google Play Movies",
        "YouTube",
        "Fandango At Home"
      ]
    },
    "VE": {
      "rent": [
        "Google Play Movies",
        "Apple TV Store"
      ],
      "buy": [
        "Google Play Movies",
        "Apple TV Store"
      ]
    },
    "ZA": {
      "rent": [
        "Apple TV Store",
        "Google Play Movies"
      ],
      "buy": [
        "Apple TV Store",
        "Google Play Movies"
      ]
    },
    "ZW": {
      "rent": [
        "Google Play Movies"
      ],
      "buy": [
        "Google Play Movies"
      ]
    }
  },
  "studios": [
    "studio_paul-gregory-productions",
    "studio_united-artists"
  ],
  "people": {
    "director": [
      "person_charles-laughton"
    ],
    "cinematography": [
      "person_stanley-cortez"
    ],
    "writer": [
      "person_charles-laughton",
      "person_james-agee"
    ],
    "editor": [
      "person_robert-golden"
    ],
    "composer": [
      "person_walter-schumann"
    ],
    "cast": [
      "person_robert-mitchum",
      "person_shelley-winters",
      "person_lillian-gish",
      "person_billy-chapin",
      "person_sally-jane-bruce",
      "person_james-gleason",
      "person_evelyn-varden",
      "person_don-beddoe",
      "person_peter-graves",
      "person_james-griffith"
    ]
  },
  "prisma_palette": {
    "primary": "claroscuro_dramatico",
    "secondary": [],
    "rank": 0.85,
    "mode": "monochromatic",
    "source": "cultural_memory",
    "temperatura_emocional": "frio_alienado",
    "ritmo_visual": "lento_contemplativo",
    "grado_abstraccion_visual": "estilizado"
  }
}