{
  "id": "work_zero-for-conduct_1933",
  "type": "film",
  "title": "Zero for Conduct",
  "original_title": "Z\u00e9ro de conduite : Jeunes diables au coll\u00e8ge",
  "year": 1933,
  "duration_min": 48,
  "synopsis": "In a repressive boarding school with rigid rules of behavior, four boys decide to rebel against the director on a celebration day.",
  "tagline": null,
  "countries": [
    "FR"
  ],
  "languages": [
    "fr"
  ],
  "ids": {
    "tmdb": 44494,
    "imdb": "tt0024803"
  },
  "genres": [
    "Comedy",
    "Drama"
  ],
  "tmdb_popularity": 0.8598,
  "media": {
    "poster_path": "/oQcGB9BGj9LPTWcEdij47McotKY.jpg",
    "backdrop_path": "/9pB6CO85B6vwwgZtBKkvyISd3Lq.jpg",
    "trailer_key": null
  },
  "where_to_watch": {
    "AO": {
      "flatrate": [
        "FilmBox+"
      ]
    },
    "AZ": {
      "flatrate": [
        "FilmBox+"
      ]
    },
    "BE": {
      "flatrate": [
        "Gaumont Amazon Channel"
      ],
      "rent": [
        "LaCinetek"
      ],
      "buy": [
        "LaCinetek"
      ]
    },
    "BF": {
      "flatrate": [
        "FilmBox+"
      ]
    },
    "BR": {
      "flatrate": [
        "Belas Artes \u00e0 La Carte"
      ]
    },
    "BY": {
      "flatrate": [
        "FilmBox+"
      ]
    },
    "BZ": {
      "flatrate": [
        "FilmBox+"
      ]
    },
    "CA": {
      "flatrate": [
        "Criterion Channel"
      ]
    },
    "CM": {
      "flatrate": [
        "FilmBox+"
      ]
    },
    "CY": {
      "flatrate": [
        "FilmBox+"
      ]
    },
    "FR": {
      "flatrate": [
        "Gaumont Amazon Channel"
      ],
      "rent": [
        "Apple TV Store",
        "Canal VOD",
        "Orange VOD",
        "LaCinetek",
        "Universcine",
        "Amazon Video",
        "VIVA by videofutur",
        "Premiere Max",
        "ARTE Boutique"
      ],
      "buy": [
        "Apple TV Store",
        "Canal VOD",
        "Orange VOD",
        "LaCinetek",
        "Universcine",
        "Amazon Video",
        "VIVA by videofutur",
        "Premiere Max",
        "ARTE Boutique"
      ]
    },
    "GY": {
      "flatrate": [
        "FilmBox+"
      ]
    },
    "IT": {
      "flatrate": [
        "MYmovies One"
      ]
    },
    "JP": {
      "flatrate": [
        "Amazon Prime Video",
        "Amazon Prime Video with Ads"
      ],
      "rent": [
        "Amazon Video"
      ],
      "buy": [
        "Amazon Video"
      ]
    },
    "LU": {
      "flatrate": [
        "FilmBox+"
      ]
    },
    "ME": {
      "flatrate": [
        "FilmBox+"
      ]
    },
    "MG": {
      "flatrate": [
        "FilmBox+"
      ]
    },
    "MK": {
      "flatrate": [
        "FilmBox+"
      ]
    },
    "ML": {
      "flatrate": [
        "FilmBox+"
      ]
    },
    "MW": {
      "flatrate": [
        "FilmBox+"
      ]
    },
    "NI": {
      "flatrate": [
        "FilmBox+"
      ]
    },
    "PG": {
      "flatrate": [
        "FilmBox+"
      ]
    },
    "RS": {
      "flatrate": [
        "FilmBox+"
      ]
    },
    "TD": {
      "flatrate": [
        "FilmBox+"
      ]
    },
    "UA": {
      "flatrate": [
        "FilmBox+"
      ]
    },
    "US": {
      "flatrate": [
        "Criterion Channel"
      ],
      "free": [
        "Darkroom"
      ]
    },
    "ZW": {
      "flatrate": [
        "FilmBox+"
      ]
    }
  },
  "studios": [
    "studio_franfilmdis",
    "studio_argui-film"
  ],
  "people": {
    "director": [
      "person_jean-vigo"
    ],
    "cinematography": [
      "person_boris-kaufman"
    ],
    "writer": [
      "person_jean-vigo"
    ],
    "editor": [
      "person_jean-vigo"
    ],
    "composer": [
      "person_maurice-jaubert"
    ],
    "cast": [
      "person_jean-daste",
      "person_robert-le-flon",
      "person_du-verron",
      "person_delphin",
      "person_leon-larive",
      "person_madame-emile",
      "person_louis-de-gonzague",
      "person_raphael-diligent",
      "person_louis-lefebvre",
      "person_gilbert-pruchon"
    ]
  },
  "prisma_palette": {
    "primary": "monocromatico_intimo",
    "secondary": [],
    "rank": 0.85,
    "mode": "monochromatic",
    "source": "cultural_memory",
    "temperatura_emocional": "calido_apasionado",
    "ritmo_visual": "dinamico_energico",
    "grado_abstraccion_visual": "estilizado"
  }
}