{
  "id": "string",
  "type": "film | short | music_video",
  "title": "string",
  "original_title": "string",
  "year": "number",
  "duration_min": "number",
  "countries": ["string"],
  "languages": ["string"],
  "ids": {
    "tmdb": "number",
    "imdb": "string",
    "wikidata": "string"
  },
  "genres": ["string"],
  "studios": ["studio_id"],
  "people": {
    "director": ["person_id"],
    "cinematography": ["person_id"],
    "writer": ["person_id"],
    "cast": ["person_id"]
  },
  "awards": [],
  "color_identity": {
    "mode": "color | monochromatic",
    "primary_color": "color_id | monochromatic_mode_id",
    "secondary_colors": ["color_id"],
    "confidence": "number (0-1)",
    "tier": "canon | core | strong | peripheral | uncertain",
    "tier_rank": "number | null (1-30 for canon, optional for core)",
    "numeric_score": "number (0-100)",
    "cultural_weight": "number (0-100)",
    "authorship_score": "number (0-100)",
    "popularity_score": "number (0-100)",
    "ai_confidence": "number (0-1)",
    "source": "ai | editorial | hybrid",
    "assigned_at": "ISO8601 timestamp"
  },
  "color_signature": {},
  "external_ratings": {},
  "media": {}
}
